LICENSE.txt
README.md
setup.cfg
setup.py
poc_tool/__init__.py
poc_tool.egg-info/PKG-INFO
poc_tool.egg-info/SOURCES.txt
poc_tool.egg-info/dependency_links.txt
poc_tool.egg-info/requires.txt
poc_tool.egg-info/top_level.txt
poc_tool/log/__init__.py
poc_tool/log/logger.py
poc_tool/tools/HexDump.py
poc_tool/tools/Tools.py
poc_tool/tools/__init__.py