Metadata-Version: 2.1
Name: poc-tool
Version: 1.2.1
Summary: Python Poc 还原原始http请求数据包以及常用工具集成化封装类，可以更快帮助您完成POC的书写及调试
Home-page: https://github.com/zhizhuoshuma/poc_tool
Author: zhizhuo
Author-email: zhizhuoshuma@163.com
License: MIT
Requires-Python: >=3.7
License-File: LICENSE.txt
Requires-Dist: requests
Requires-Dist: colorama
